pyecharts_javascripthon/__init__.py
pyecharts_javascripthon/_version.py
pyecharts_javascripthon/api.py
pyecharts_javascripthon/client.py
pyecharts_javascripthon/compat.py
pyecharts_javascripthon/compiler.py
pyecharts_javascripthon/dom.py
pyecharts_javascripthon-0.0.5.dist-info/DESCRIPTION.rst
pyecharts_javascripthon-0.0.5.dist-info/METADATA
pyecharts_javascripthon-0.0.5.dist-info/RECORD
pyecharts_javascripthon-0.0.5.dist-info/WHEEL
pyecharts_javascripthon-0.0.5.dist-info/metadata.json
pyecharts_javascripthon-0.0.5.dist-info/top_level.txt
