Metadata-Version: 1.1
Name: pyecharts-javascripthon
Version: 0.0.5
Summary: Embeded Python functions in pyecharts
Home-page: https://github.com/pyecharts/pyecharts-javascripthon
Author: C.W.
Author-email: wangc_2011@hotmail.com
License: MIT
Download-URL: https://github.com/pyecharts/pyecharts-javascripthon/archive/0.0.5.tar.gz
Keywords: python
Platform: UNKNOWN
Classifier: Topic :: Office/Business
Classifier: Topic :: Utilities
Classifier: Topic :: Software Development :: Libraries
Classifier: Programming Language :: Python
Classifier: Intended Audience :: Developers
Classifier: Programming Language :: Python :: 2.6
Classifier: Programming Language :: Python :: 2.7
Classifier: Programming Language :: Python :: 3.3
Classifier: Programming Language :: Python :: 3.4
Classifier: Programming Language :: Python :: 3.5
Classifier: Programming Language :: Python :: 3.6
